README.md
setup.py
pierskarsenbarg_pulumi_sdm/__init__.py
pierskarsenbarg_pulumi_sdm/_inputs.py
pierskarsenbarg_pulumi_sdm/_utilities.py
pierskarsenbarg_pulumi_sdm/account.py
pierskarsenbarg_pulumi_sdm/account_attachment.py
pierskarsenbarg_pulumi_sdm/account_group.py
pierskarsenbarg_pulumi_sdm/approval_workflow.py
pierskarsenbarg_pulumi_sdm/approval_workflow_approver.py
pierskarsenbarg_pulumi_sdm/approval_workflow_step.py
pierskarsenbarg_pulumi_sdm/get_account.py
pierskarsenbarg_pulumi_sdm/get_account_attachment.py
pierskarsenbarg_pulumi_sdm/get_account_group.py
pierskarsenbarg_pulumi_sdm/get_approval_workflow.py
pierskarsenbarg_pulumi_sdm/get_approval_workflow_approver.py
pierskarsenbarg_pulumi_sdm/get_approval_workflow_step.py
pierskarsenbarg_pulumi_sdm/get_group.py
pierskarsenbarg_pulumi_sdm/get_group_role.py
pierskarsenbarg_pulumi_sdm/get_identity_alias.py
pierskarsenbarg_pulumi_sdm/get_identity_set.py
pierskarsenbarg_pulumi_sdm/get_managed_secret.py
pierskarsenbarg_pulumi_sdm/get_node.py
pierskarsenbarg_pulumi_sdm/get_peering_group.py
pierskarsenbarg_pulumi_sdm/get_peering_group_node.py
pierskarsenbarg_pulumi_sdm/get_peering_group_peer.py
pierskarsenbarg_pulumi_sdm/get_peering_group_resource.py
pierskarsenbarg_pulumi_sdm/get_policy.py
pierskarsenbarg_pulumi_sdm/get_proxy_cluster_key.py
pierskarsenbarg_pulumi_sdm/get_rdp_ca_pubkey.py
pierskarsenbarg_pulumi_sdm/get_remote_identity.py
pierskarsenbarg_pulumi_sdm/get_remote_identity_group.py
pierskarsenbarg_pulumi_sdm/get_resource.py
pierskarsenbarg_pulumi_sdm/get_role.py
pierskarsenbarg_pulumi_sdm/get_secret_engine.py
pierskarsenbarg_pulumi_sdm/get_secret_store.py
pierskarsenbarg_pulumi_sdm/get_ssh_ca_pubkey.py
pierskarsenbarg_pulumi_sdm/get_workflow.py
pierskarsenbarg_pulumi_sdm/get_workflow_approver.py
pierskarsenbarg_pulumi_sdm/get_workflow_role.py
pierskarsenbarg_pulumi_sdm/group.py
pierskarsenbarg_pulumi_sdm/group_role.py
pierskarsenbarg_pulumi_sdm/identity_alias.py
pierskarsenbarg_pulumi_sdm/identity_set.py
pierskarsenbarg_pulumi_sdm.egg-info/PKG-INFO
pierskarsenbarg_pulumi_sdm.egg-info/SOURCES.txt
pierskarsenbarg_pulumi_sdm.egg-info/dependency_links.txt
pierskarsenbarg_pulumi_sdm.egg-info/not-zip-safe
pierskarsenbarg_pulumi_sdm.egg-info/requires.txt
pierskarsenbarg_pulumi_sdm.egg-info/top_level.txt
