Metadata-Version: 2.1
Name: pierskarsenbarg-pulumi-sdm
Version: 1.32.0
Summary: A Pulumi package for creating and managing StrongDM cloud resources.
Home-page: https://github.com/pierskarsenbarg/pulumi-sdm
License: Apache-2.0
Project-URL: Repository, https://github.com/pierskarsenbarg/pulumi-sdm
Keywords: pulumi sdm category/cloud
Requires-Python: >=3.9
